ccs/__init__.py
ccs/core.py
ccs/init.py
ccs/utils.py
ccs/api/__init__.py
ccs/api/get_concept.py
ccs/api/get_connection.py
ccs/api/http_client.py
ccs/api/oauth.py
ccs/api/search/__init__.py
ccs/api/search/freeschema_query_api.py
ccs/api/search/schema_query_listener.py
ccs/config/__init__.py
ccs/config/base_url.py
ccs/config/token_storage.py
ccs/constants/__init__.py
ccs/constants/format_constants.py
ccs/data/__init__.py
ccs/data/inner_actions.py
ccs/data/local_concept_data.py
ccs/data/local_connection_data.py
ccs/data/local_id.py
ccs/data/local_sync_data.py
ccs/models/__init__.py
ccs/models/concept.py
ccs/models/connection.py
ccs/models/search/__init__.py
ccs/models/search/filter_search.py
ccs/models/search/freeschema_query.py
ccs/services/__init__.py
ccs/services/get/__init__.py
ccs/services/get/get_the_concept.py
ccs/services/local/__init__.py
ccs/services/local/create_the_concept_local.py
ccs/services/local/create_the_connection_local.py
ccs/services/local/get_concept_by_character_local.py
ccs/services/local/helpers.py
ccs/services/local/make_the_concept_local.py
ccs/services/local/make_the_instance_concept_local.py
ccs/services/local/make_the_type_local.py
ccs/services/search/__init__.py
ccs/services/search/count_info.py
ccs/services/search/data_id_format.py
ccs/services/search/flatten.py
ccs/services/search/ordering.py
ccs/services/search/prefetch.py
ccs/services/transaction/__init__.py
ccs/services/transaction/local_transaction.py
mftsccs-0.1.12.dist-info/licenses/LICENSE
mftsccs-0.1.12.dist-info/METADATA
mftsccs-0.1.12.dist-info/WHEEL
mftsccs-0.1.12.dist-info/top_level.txt
mftsccs-0.1.12.dist-info/RECORD
