Metadata-Version: 2.4
Name: mftsccs
Version: 0.1.12
Summary: A Python library for Concept-Connection System (CCS) - offline-first knowledge graph management
Author-email: Boomconsole <nischal@boomconsole.com>
License: MIT
Project-URL: Homepage, https://freeschema.com
Project-URL: Documentation, https://freeschema.com
Project-URL: Repository, https://github.com/Mentor-Friends/CCS-PYTHON
Project-URL: Issues, https://github.com/Mentor-Friends/CCS-PYTHON/issues
Keywords: ccs,library,utilities
Classifier: Development Status :: 3 - Alpha
Classifier: Intended Audience :: Developers
Classifier: License :: OSI Approved :: MIT License
Classifier: Operating System :: OS Independent
Classifier: Programming Language :: Python :: 3
Classifier: Programming Language :: Python :: 3.8
Classifier: Programming Language :: Python :: 3.9
Classifier: Programming Language :: Python :: 3.10
Classifier: Programming Language :: Python :: 3.11
Classifier: Programming Language :: Python :: 3.12
Requires-Python: >=3.8
License-File: LICENSE
Requires-Dist: aiohttp>=3.8.0
Provides-Extra: dev
Requires-Dist: pytest>=7.0; extra == "dev"
Requires-Dist: pytest-cov>=4.0; extra == "dev"
Requires-Dist: black>=23.0; extra == "dev"
Requires-Dist: ruff>=0.1.0; extra == "dev"
Requires-Dist: mypy>=1.0; extra == "dev"
Dynamic: license-file
